dokr_pkg/__init__.py
dokr_pkg/anonymous_matlab.py
dokr_pkg/try1.py
try1.py-0.1.data/scripts/abc_matlab.py
try1.py-0.1.data/scripts/anonymous_matlab.py
try1.py-0.1.data/scripts/try1.py
try1.py-0.1.dist-info/METADATA
try1.py-0.1.dist-info/WHEEL
try1.py-0.1.dist-info/top_level.txt
try1.py-0.1.dist-info/RECORD
